src/__init__.py
src/_version.py
src/circlecigen.py
src/template.py
src/tfvars.py
src/utils.py
circlecigen-0.1.0.dist-info/LICENSE
circlecigen-0.1.0.dist-info/METADATA
circlecigen-0.1.0.dist-info/WHEEL
circlecigen-0.1.0.dist-info/entry_points.txt
circlecigen-0.1.0.dist-info/top_level.txt
circlecigen-0.1.0.dist-info/RECORD
