Metadata-Version: 2.1
Name: circlecigen
Version: 0.1.0
Summary: Opinionated generation of continuation pipelines
Home-page: https://github.com/ThoughtWorks-DPS/circlecigen
Author: Nic Cheneweth
Author-email: Nic Cheneweth <nchenewe@thoughtworks.com>
Project-URL: Homepage, https://github.com/ThoughtWorks-DPS/circlecigen
Project-URL: Bug Tracker, https://github.com/ThoughtWorks-DPS/circlecigen/issues
Classifier: Programming Language :: Python :: 3
Classifier: License :: OSI Approved :: MIT License
Classifier: Operating System :: OS Independent
Requires-Python: >=3.7
License-File: LICENSE
Requires-Dist: click
Requires-Dist: pathvalidate
Requires-Dist: jinja2
